sahara_tempest_plugin/README.rst
sahara_tempest_plugin/__init__.py
sahara_tempest_plugin/clients.py
sahara_tempest_plugin/config.py
sahara_tempest_plugin/plugin.py
sahara_tempest_plugin/common/__init__.py
sahara_tempest_plugin/common/plugin_utils.py
sahara_tempest_plugin/services/__init__.py
sahara_tempest_plugin/services/data_processing/__init__.py
sahara_tempest_plugin/services/data_processing/base_client.py
sahara_tempest_plugin/services/data_processing/v1_1/__init__.py
sahara_tempest_plugin/services/data_processing/v1_1/data_processing_client.py
sahara_tempest_plugin/services/data_processing/v2/__init__.py
sahara_tempest_plugin/services/data_processing/v2/data_processing_client.py
sahara_tempest_plugin/tests/__init__.py
sahara_tempest_plugin/tests/api/__init__.py
sahara_tempest_plugin/tests/api/base.py
sahara_tempest_plugin/tests/api/test_cluster_templates.py
sahara_tempest_plugin/tests/api/test_data_sources.py
sahara_tempest_plugin/tests/api/test_job_binaries.py
sahara_tempest_plugin/tests/api/test_job_binary_internals.py
sahara_tempest_plugin/tests/api/test_job_templates.py
sahara_tempest_plugin/tests/api/test_jobs.py
sahara_tempest_plugin/tests/api/test_node_group_templates.py
sahara_tempest_plugin/tests/api/test_plugins.py
sahara_tempest_plugin/tests/cli/README.rst
sahara_tempest_plugin/tests/cli/__init__.py
sahara_tempest_plugin/tests/cli/base.py
sahara_tempest_plugin/tests/cli/cluster_templates.py
sahara_tempest_plugin/tests/cli/clusters.py
sahara_tempest_plugin/tests/cli/data_sources.py
sahara_tempest_plugin/tests/cli/images.py
sahara_tempest_plugin/tests/cli/job_binaries.py
sahara_tempest_plugin/tests/cli/job_templates.py
sahara_tempest_plugin/tests/cli/job_types.py
sahara_tempest_plugin/tests/cli/jobs.py
sahara_tempest_plugin/tests/cli/node_group_templates.py
sahara_tempest_plugin/tests/cli/plugins.py
sahara_tempest_plugin/tests/cli/test_scenario.py
sahara_tempest_plugin/tests/clients/__init__.py
sahara_tempest_plugin/tests/clients/base.py
sahara_tests-0.18.0.dist-info/AUTHORS
sahara_tests-0.18.0.dist-info/LICENSE
sahara_tests-0.18.0.dist-info/METADATA
sahara_tests-0.18.0.dist-info/WHEEL
sahara_tests-0.18.0.dist-info/entry_points.txt
sahara_tests-0.18.0.dist-info/pbr.json
sahara_tests-0.18.0.dist-info/top_level.txt
sahara_tests-0.18.0.dist-info/RECORD
